{
  "gitSyncId": "689d89d0c8cfcc46e1c3653b_f90b228a-63a6-4e0b-8ec5-1c1e108aa8ac",
  "id": "Audit Department_IssueHelpers.addWorkingDaysLocal",
  "pluginId": "js-plugin",
  "pluginType": "JS",
  "unpublishedAction": {
    "actionConfiguration": {
      "encodeParamsToggle": true,
      "jsArguments": [
        {
          "name": "startDate"
        },
        {
          "name": "days"
        },
        {
          "name": "holidaysRows"
        }
      ],
      "paginationType": "NONE",
      "timeoutInMillisecond": 10000
    },
    "collectionId": "Audit Department_IssueHelpers",
    "confirmBeforeExecute": false,
    "datasource": {
      "isAutoGenerated": false,
      "name": "UNUSED_DATASOURCE",
      "pluginId": "js-plugin"
    },
    "dynamicBindingPathList": [
      {
        "key": "body"
      }
    ],
    "fullyQualifiedName": "IssueHelpers.addWorkingDaysLocal",
    "name": "addWorkingDaysLocal",
    "pageId": "Audit Department",
    "runBehaviour": "MANUAL",
    "userSetOnLoad": false
  }
}