{
  "gitSyncId": "689d89d0c8cfcc46e1c3653b_8e6b07d3-a964-4798-a27f-ad229ecca16e",
  "id": "Report Overview_ReviewActions.allSignoffs",
  "pluginId": "js-plugin",
  "pluginType": "JS",
  "unpublishedAction": {
    "actionConfiguration": {
      "encodeParamsToggle": true,
      "jsArguments": [],
      "paginationType": "NONE",
      "timeoutInMillisecond": 10000
    },
    "collectionId": "Report Overview_ReviewActions",
    "confirmBeforeExecute": false,
    "datasource": {
      "isAutoGenerated": false,
      "name": "UNUSED_DATASOURCE",
      "pluginId": "js-plugin"
    },
    "dynamicBindingPathList": [
      {
        "key": "body"
      }
    ],
    "fullyQualifiedName": "ReviewActions.allSignoffs",
    "name": "allSignoffs",
    "pageId": "Report Overview",
    "runBehaviour": "MANUAL",
    "userSetOnLoad": false
  }
}