{
  "gitSyncId": "689d89d0c8cfcc46e1c3653b_589f67c8-d934-4c2d-a9dc-7fa4eda35182",
  "id": "Review OFI_ReviewOFi.commentAttention",
  "pluginId": "js-plugin",
  "pluginType": "JS",
  "unpublishedAction": {
    "actionConfiguration": {
      "encodeParamsToggle": true,
      "jsArguments": [],
      "paginationType": "NONE",
      "timeoutInMillisecond": 10000
    },
    "collectionId": "Review OFI_ReviewOFi",
    "confirmBeforeExecute": false,
    "datasource": {
      "isAutoGenerated": false,
      "name": "UNUSED_DATASOURCE",
      "pluginId": "js-plugin"
    },
    "dynamicBindingPathList": [
      {
        "key": "body"
      }
    ],
    "fullyQualifiedName": "ReviewOFi.commentAttention",
    "name": "commentAttention",
    "pageId": "Review OFI",
    "runBehaviour": "MANUAL",
    "userSetOnLoad": false
  }
}