{
  "gitSyncId": "689d89d0c8cfcc46e1c3653b_b9c21b94-d39e-4fa7-a226-842f9cd52daf",
  "id": "Verify OFI Evidence_EvidenceActions._rawUrl",
  "pluginId": "js-plugin",
  "pluginType": "JS",
  "unpublishedAction": {
    "actionConfiguration": {
      "encodeParamsToggle": true,
      "jsArguments": [
        {
          "name": "fid"
        },
        {
          "name": "name"
        }
      ],
      "paginationType": "NONE",
      "timeoutInMillisecond": 10000
    },
    "collectionId": "Verify OFI Evidence_EvidenceActions",
    "confirmBeforeExecute": false,
    "datasource": {
      "isAutoGenerated": false,
      "name": "UNUSED_DATASOURCE",
      "pluginId": "js-plugin"
    },
    "dynamicBindingPathList": [
      {
        "key": "body"
      }
    ],
    "fullyQualifiedName": "EvidenceActions._rawUrl",
    "name": "_rawUrl",
    "pageId": "Verify OFI Evidence",
    "runBehaviour": "MANUAL",
    "userSetOnLoad": false
  }
}