{
  "gitSyncId": "689d89d0c8cfcc46e1c3653b_d5dabebd-5cf2-4c5d-a349-8e1577e0b9c2",
  "id": "Verify OFI Plan_VerifyOFI.obsNo",
  "pluginId": "js-plugin",
  "pluginType": "JS",
  "unpublishedAction": {
    "actionConfiguration": {
      "encodeParamsToggle": true,
      "jsArguments": [],
      "paginationType": "NONE",
      "timeoutInMillisecond": 10000
    },
    "collectionId": "Verify OFI Plan_VerifyOFI",
    "confirmBeforeExecute": false,
    "datasource": {
      "isAutoGenerated": false,
      "name": "UNUSED_DATASOURCE",
      "pluginId": "js-plugin"
    },
    "dynamicBindingPathList": [
      {
        "key": "body"
      }
    ],
    "fullyQualifiedName": "VerifyOFI.obsNo",
    "name": "obsNo",
    "pageId": "Verify OFI Plan",
    "runBehaviour": "MANUAL",
    "userSetOnLoad": false
  }
}