{
  "gitSyncId": "689d89d0c8cfcc46e1c3653b_60af46a9-3a0e-4620-95e3-c972708b2d72",
  "id": "Audit Department_Holidays_GetAll",
  "pluginId": "google-sheets-plugin",
  "pluginType": "SAAS",
  "unpublishedAction": {
    "actionConfiguration": {
      "encodeParamsToggle": true,
      "formData": {
        "command": {
          "data": "FETCH_MANY"
        },
        "entityType": {
          "data": "ROWS"
        },
        "pagination": {
          "data": {
            "limit": "20",
            "offset": "0"
          }
        },
        "projection": {
          "data": []
        },
        "queryFormat": {
          "data": "ROWS"
        },
        "range": {
          "data": ""
        },
        "sheetName": {
          "data": "holidays"
        },
        "sheetUrl": {
          "data": "https://docs.google.com/spreadsheets/d/1rQShK0AWzpID6eZ2tiTGibrVDmyLSC2q6jMpbA8iUkA/edit"
        },
        "smartSubstitution": {
          "data": true
        },
        "sortBy": {
          "data": [
            {
              "column": "",
              "order": "Ascending"
            }
          ]
        },
        "tableHeaderIndex": {
          "data": "1"
        },
        "where": {
          "data": {
            "children": [
              {
                "condition": "LT"
              }
            ],
            "condition": "AND"
          }
        }
      },
      "paginationType": "NONE",
      "timeoutInMillisecond": 10000
    },
    "confirmBeforeExecute": false,
    "datasource": {
      "id": "GS_FormWorkflow",
      "isAutoGenerated": false,
      "name": "GS_FormWorkflow",
      "pluginId": "google-sheets-plugin"
    },
    "dynamicBindingPathList": [],
    "name": "Holidays_GetAll",
    "pageId": "Audit Department",
    "runBehaviour": "AUTOMATIC",
    "userSetOnLoad": false
  }
}