{
  "gitSyncId": "689d89d0c8cfcc46e1c3653b_8bca85ee-2c71-41f1-81f4-cedbbc53fa0b",
  "id": "Verify OFI Plan_NCFinding._formId",
  "pluginId": "js-plugin",
  "pluginType": "JS",
  "unpublishedAction": {
    "actionConfiguration": {
      "encodeParamsToggle": true,
      "jsArguments": [],
      "paginationType": "NONE",
      "timeoutInMillisecond": 10000
    },
    "collectionId": "Verify OFI Plan_NCFinding",
    "confirmBeforeExecute": false,
    "datasource": {
      "isAutoGenerated": false,
      "name": "UNUSED_DATASOURCE",
      "pluginId": "js-plugin"
    },
    "dynamicBindingPathList": [
      {
        "key": "body"
      }
    ],
    "fullyQualifiedName": "NCFinding._formId",
    "name": "_formId",
    "pageId": "Verify OFI Plan",
    "runBehaviour": "MANUAL",
    "userSetOnLoad": false
  }
}