{
  "gitSyncId": "689d89d0c8cfcc46e1c3653b_5c9755db-ab28-49e9-b8d2-b5350014a14d",
  "id": "Create Finding_COMMENT.nextObsCode",
  "pluginId": "js-plugin",
  "pluginType": "JS",
  "unpublishedAction": {
    "actionConfiguration": {
      "encodeParamsToggle": true,
      "jsArguments": [
        {
          "name": "rows"
        }
      ],
      "paginationType": "NONE",
      "timeoutInMillisecond": 10000
    },
    "collectionId": "Create Finding_COMMENT",
    "confirmBeforeExecute": false,
    "datasource": {
      "isAutoGenerated": false,
      "name": "UNUSED_DATASOURCE",
      "pluginId": "js-plugin"
    },
    "dynamicBindingPathList": [
      {
        "key": "body"
      }
    ],
    "fullyQualifiedName": "COMMENT.nextObsCode",
    "name": "nextObsCode",
    "pageId": "Create Finding",
    "runBehaviour": "MANUAL",
    "userSetOnLoad": false
  }
}