{
  "gitSyncId": "689d89d0c8cfcc46e1c3653b_1c4a7b76-b468-4b00-be13-4e5552fb80d9",
  "id": "Report Overview_VerifyOFI.ofiTargetDate",
  "pluginId": "js-plugin",
  "pluginType": "JS",
  "unpublishedAction": {
    "actionConfiguration": {
      "encodeParamsToggle": true,
      "jsArguments": [],
      "paginationType": "NONE",
      "timeoutInMillisecond": 10000
    },
    "collectionId": "Report Overview_VerifyOFI",
    "confirmBeforeExecute": false,
    "datasource": {
      "isAutoGenerated": false,
      "name": "UNUSED_DATASOURCE",
      "pluginId": "js-plugin"
    },
    "dynamicBindingPathList": [
      {
        "key": "body"
      }
    ],
    "fullyQualifiedName": "VerifyOFI.ofiTargetDate",
    "name": "ofiTargetDate",
    "pageId": "Report Overview",
    "runBehaviour": "MANUAL",
    "userSetOnLoad": false
  }
}