{
  "gitSyncId": "689d89d0c8cfcc46e1c3653b_33f9797c-5f0e-4b6b-9452-afd123dc8ef6",
  "id": "Review OFI_NCViewer.viewLatest",
  "pluginId": "js-plugin",
  "pluginType": "JS",
  "unpublishedAction": {
    "actionConfiguration": {
      "encodeParamsToggle": true,
      "jsArguments": [
        {
          "name": "fid"
        }
      ],
      "paginationType": "NONE",
      "timeoutInMillisecond": 10000
    },
    "collectionId": "Review OFI_NCViewer",
    "confirmBeforeExecute": false,
    "datasource": {
      "isAutoGenerated": false,
      "name": "UNUSED_DATASOURCE",
      "pluginId": "js-plugin"
    },
    "dynamicBindingPathList": [
      {
        "key": "body"
      }
    ],
    "fullyQualifiedName": "NCViewer.viewLatest",
    "name": "viewLatest",
    "pageId": "Review OFI",
    "runBehaviour": "MANUAL",
    "userSetOnLoad": false
  }
}