{
  "gitSyncId": "689d89d0c8cfcc46e1c3653b_e29a05a5-b366-467c-bc94-daf182e6f888",
  "id": "Verify OFI Evidence_VerifyOFI_Yellow.yellowLatestCommentDate",
  "pluginId": "js-plugin",
  "pluginType": "JS",
  "unpublishedAction": {
    "actionConfiguration": {
      "encodeParamsToggle": true,
      "jsArguments": [
        {
          "name": "role"
        },
        {
          "name": "fmt",
          "value": "YYYY-MM-DD HH:mm:ss"
        }
      ],
      "paginationType": "NONE",
      "timeoutInMillisecond": 10000
    },
    "collectionId": "Verify OFI Evidence_VerifyOFI_Yellow",
    "confirmBeforeExecute": false,
    "datasource": {
      "isAutoGenerated": false,
      "name": "UNUSED_DATASOURCE",
      "pluginId": "js-plugin"
    },
    "dynamicBindingPathList": [
      {
        "key": "body"
      }
    ],
    "fullyQualifiedName": "VerifyOFI_Yellow.yellowLatestCommentDate",
    "name": "yellowLatestCommentDate",
    "pageId": "Verify OFI Evidence",
    "runBehaviour": "MANUAL",
    "userSetOnLoad": false
  }
}