{
  "gitSyncId": "689d89d0c8cfcc46e1c3653b_fe77c354-e8ed-403e-a6fb-700bea9fcd91",
  "id": "Report Overview_ReviewOFi.statusForHeader",
  "pluginId": "js-plugin",
  "pluginType": "JS",
  "unpublishedAction": {
    "actionConfiguration": {
      "encodeParamsToggle": true,
      "jsArguments": [],
      "paginationType": "NONE",
      "timeoutInMillisecond": 10000
    },
    "collectionId": "Report Overview_ReviewOFi",
    "confirmBeforeExecute": false,
    "datasource": {
      "isAutoGenerated": false,
      "name": "UNUSED_DATASOURCE",
      "pluginId": "js-plugin"
    },
    "dynamicBindingPathList": [
      {
        "key": "body"
      }
    ],
    "fullyQualifiedName": "ReviewOFi.statusForHeader",
    "name": "statusForHeader",
    "pageId": "Report Overview",
    "runBehaviour": "MANUAL",
    "userSetOnLoad": false
  }
}