{
  "gitSyncId": "689d89d0c8cfcc46e1c3653b_0fa715b6-de38-41d6-8f3c-fba36f2425f3",
  "id": "Verify OFI Evidence_Utils.addWorkingDays",
  "pluginId": "js-plugin",
  "pluginType": "JS",
  "unpublishedAction": {
    "actionConfiguration": {
      "encodeParamsToggle": true,
      "jsArguments": [
        {
          "name": "startDateInput"
        },
        {
          "name": "n"
        },
        {
          "name": "holidays",
          "value": "{{[]}}"
        }
      ],
      "paginationType": "NONE",
      "timeoutInMillisecond": 10000
    },
    "collectionId": "Verify OFI Evidence_Utils",
    "confirmBeforeExecute": false,
    "datasource": {
      "isAutoGenerated": false,
      "name": "UNUSED_DATASOURCE",
      "pluginId": "js-plugin"
    },
    "dynamicBindingPathList": [
      {
        "key": "body"
      }
    ],
    "fullyQualifiedName": "Utils.addWorkingDays",
    "name": "addWorkingDays",
    "pageId": "Verify OFI Evidence",
    "runBehaviour": "MANUAL",
    "userSetOnLoad": false
  }
}