{
  "gitSyncId": "689d89d0c8cfcc46e1c3653b_be1eee26-2e18-43bf-97c7-d3bac09559d9",
  "id": "Approval Finding_ReviewActions.isApproved",
  "pluginId": "js-plugin",
  "pluginType": "JS",
  "unpublishedAction": {
    "actionConfiguration": {
      "encodeParamsToggle": true,
      "jsArguments": [
        {
          "name": "role"
        }
      ],
      "paginationType": "NONE",
      "timeoutInMillisecond": 10000
    },
    "collectionId": "Approval Finding_ReviewActions",
    "confirmBeforeExecute": false,
    "datasource": {
      "isAutoGenerated": false,
      "name": "UNUSED_DATASOURCE",
      "pluginId": "js-plugin"
    },
    "dynamicBindingPathList": [
      {
        "key": "body"
      }
    ],
    "fullyQualifiedName": "ReviewActions.isApproved",
    "name": "isApproved",
    "pageId": "Approval Finding",
    "runBehaviour": "MANUAL",
    "userSetOnLoad": false
  }
}